qianghua_evn/__init__.py
qianghua_evn/envs/__init__.py
qianghua_evn-0.0.1.dist-info/METADATA
qianghua_evn-0.0.1.dist-info/WHEEL
qianghua_evn-0.0.1.dist-info/top_level.txt
qianghua_evn-0.0.1.dist-info/RECORD
